tonggong/__init__.py
tonggong/base62.py
tonggong/bunch.py
tonggong/constant.py
tonggong/converter.py
tonggong/crontab.py
tonggong/enum.py
tonggong/formatter.py
tonggong/generator.py
tonggong/hash.py
tonggong/isoweek.py
tonggong/redis.py
tonggong/unittest.py
tonggong/util.py
tonggong/django/__init__.py
tonggong/django/model.py
tonggong/validations/__init__.py
tonggong/validations/errors.py
tonggong/validations/utils.py
tonggong/validations/validators.py
tonggong-1.0.4.dist-info/LICENSE
tonggong-1.0.4.dist-info/METADATA
tonggong-1.0.4.dist-info/WHEEL
tonggong-1.0.4.dist-info/top_level.txt
tonggong-1.0.4.dist-info/RECORD
