Metadata-Version: 2.1
Name: tonggong
Version: 1.0.4
Summary: Universal toolkit
Home-page: https://github.com/arcticdata/tonggong
Author: Arctic Data
Author-email: hello@datarc.cn
License: MIT License
Classifier: License :: OSI Approved :: MIT License
Classifier: Programming Language :: Python :: 3
Classifier: Programming Language :: Python :: 3.8
Classifier: Programming Language :: Python :: 3.9
Classifier: Programming Language :: Python :: 3.10
Classifier: Programming Language :: Python :: 3.11
Classifier: Programming Language :: Python :: 3.12
Classifier: Programming Language :: Python :: 3.13
License-File: LICENSE
